advanced_memory_controller.v
module advanced_memory_controller #(
    parameter ADDR_WIDTH = 6,
    parameter DATA_WIDTH = 32,
    parameter DEPTH      = 64
)(
    input  wire                  clk,
    input  wire                  rst,

    input  wire                  write_en,
    input  wire                  read_en,
    input  wire [ADDR_WIDTH-1:0] addr,
    input  wire [DATA_WIDTH-1:0] write_data,

    output reg  [DATA_WIDTH-1:0] read_data,
    output reg                   read_valid,
    output reg                   busy
);

    reg [DATA_WIDTH-1:0] memory [0:DEPTH-1];

    always @(posedge clk) begin
        if (rst) begin
            read_data  <= {DATA_WIDTH{1'b0}};
            read_valid <= 1'b0;
            busy       <= 1'b0;
        end
        else begin
            read_valid <= 1'b0;
            busy       <= 1'b0;

            if (write_en) begin
                memory[addr] <= write_data;
                busy <= 1'b1;
            end

            if (read_en) begin
                read_data  <= memory[addr];
                read_valid <= 1'b1;
                busy       <= 1'b1;
            end
        end
    end

endmodule

tb_advanced_memory_controller.v
`timescale 1ns/1ps

module tb_advanced_memory_controller;

    parameter ADDR_WIDTH = 6;
    parameter DATA_WIDTH = 32;
    parameter DEPTH      = 64;

    reg                   clk;
    reg                   rst;
    reg                   write_en;
    reg                   read_en;
    reg  [ADDR_WIDTH-1:0] addr;
    reg  [DATA_WIDTH-1:0] write_data;

    wire [DATA_WIDTH-1:0] read_data;
    wire                  read_valid;
    wire                  busy;

    advanced_memory_controller #(
        .ADDR_WIDTH(ADDR_WIDTH),
        .DATA_WIDTH(DATA_WIDTH),
        .DEPTH(DEPTH)
    ) dut (
        .clk(clk),
        .rst(rst),
        .write_en(write_en),
        .read_en(read_en),
        .addr(addr),
        .write_data(write_data),
        .read_data(read_data),
        .read_valid(read_valid),
        .busy(busy)
    );

    always #5 clk = ~clk;

    initial begin
        $dumpfile("sim/advanced_memory_controller.vcd");
        $dumpvars(0, tb_advanced_memory_controller);
    end

    initial begin

        clk        = 1'b0;
        rst        = 1'b1;
        write_en   = 1'b0;
        read_en    = 1'b0;
        addr       = 6'd0;
        write_data = 32'd0;

        #20;
        rst = 1'b0;

        // WRITE 1
        @(negedge clk);
        addr       = 6'd10;
        write_data = 32'hDEADBEEF;
        write_en   = 1'b1;

        @(negedge clk);
        write_en = 1'b0;

        // READ 1
        @(negedge clk);
        addr    = 6'd10;
        read_en = 1'b1;

        @(negedge clk);
        read_en = 1'b0;

        @(posedge clk);

        $display("READ 1");
        $display("Address = %d", addr);
        $display("Data    = %h", read_data);

        if (read_data == 32'hDEADBEEF)
            $display("READ 1 TEST: PASS");
        else
            $display("READ 1 TEST: FAIL");

        // WRITE 2
        @(negedge clk);
        addr       = 6'd25;
        write_data = 32'h12345678;
        write_en   = 1'b1;

        @(negedge clk);
        write_en = 1'b0;

        // READ 2
        @(negedge clk);
        addr    = 6'd25;
        read_en = 1'b1;

        @(negedge clk);
        read_en = 1'b0;

        @(posedge clk);

        $display("READ 2");
        $display("Address = %d", addr);
        $display("Data    = %h", read_data);

        if (read_data == 32'h12345678)
            $display("READ 2 TEST: PASS");
        else
            $display("READ 2 TEST: FAIL");

        #20;

        $display("==========================================");
        $display("Advanced Memory Controller Test Complete");
        $display("==========================================");

        $finish;

    end

endmodule

advanced_memory_controller.vcd
$date
	Sat Sep 19 23:43:10 2026
$end
$version
	Icarus Verilog
$end
$timescale
	1ps
$end
$scope module tb_advanced_memory_controller $end
$var wire 1 ! read_valid $end
$var wire 32 " read_data [31:0] $end
$var wire 1 # busy $end
$var parameter 32 $ ADDR_WIDTH $end
$var parameter 32 % DATA_WIDTH $end
$var parameter 32 & DEPTH $end
$var reg 6 ' addr [5:0] $end
$var reg 1 ( clk $end
$var reg 1 ) read_en $end
$var reg 1 * rst $end
$var reg 32 + write_data [31:0] $end
$var reg 1 , write_en $end
$scope module dut $end
$var wire 6 - addr [5:0] $end
$var wire 1 ( clk $end
$var wire 1 ) read_en $end
$var wire 1 * rst $end
$var wire 32 . write_data [31:0] $end
$var wire 1 , write_en $end
$var parameter 32 / ADDR_WIDTH $end
$var parameter 32 0 DATA_WIDTH $end
$var parameter 32 1 DEPTH $end
$var reg 1 # busy $end
$var reg 32 2 read_data [31:0] $end
$var reg 1 ! read_valid $end
$upscope $end
$upscope $end
$enddefinitions $end
$comment Show the parameter values. $end
$dumpall
b1000000 1
b100000 0
b110 /
b1000000 &
b100000 %
b110 $
$end
#0
$dumpvars
bx 2
b0 .
b0 -
0,
b0 +
1*
0)
0(
b0 '
x#
bx "
x!
$end
#5000
0#
0!
b0 "
b0 2
1(
#10000
0(
#15000
1(
#20000
1,
b11011110101011011011111011101111 +
b11011110101011011011111011101111 .
b1010 '
b1010 -
0(
0*
#25000
1#
1(
#30000
0,
0(
#35000
0#
1(
#40000
1)
0(
#45000
1#
1!
b11011110101011011011111011101111 "
b11011110101011011011111011101111 2
1(
#50000
0)
0(
#55000
0#
0!
1(
#60000
1,
b10010001101000101011001111000 +
b10010001101000101011001111000 .
b11001 '
b11001 -
0(
#65000
1#
1(
#70000
0,
0(
#75000
0#
1(
#80000
1)
0(
#85000
1#
1!
b10010001101000101011001111000 "
b10010001101000101011001111000 2
1(
#90000
0)
0(
#95000
0#
0!
1(
